g3hardware/__init__.py
g3hardware/_g3hardware.py
g3hardware/api.py
g3hardware/config.yaml
g3hardware/py.typed
g3hardware-0.2.13.dist-info/licenses/LICENCE
g3hardware-0.2.13.dist-info/METADATA
g3hardware-0.2.13.dist-info/WHEEL
g3hardware-0.2.13.dist-info/top_level.txt
g3hardware-0.2.13.dist-info/RECORD
