Metadata-Version: 2.4
Name: g3hardware
Version: 0.2.13
Summary: G3 PLC Hardware XML configuration generator
Author: Elektroline a.s.
Project-URL: Homepage, https://gitlab.elektroline.cz/plc/systemg3-py/SystemG3Hardware
Classifier: Development Status :: 3 - Alpha
Classifier: Intended Audience :: Developers
Classifier: Intended Audience :: Other Audience
Classifier: License :: OSI Approved :: MIT License
Classifier: Natural Language :: English
Classifier: Operating System :: OS Independent
Classifier: Programming Language :: Python :: 3
Classifier: Programming Language :: Python :: 3 :: Only
Classifier: Programming Language :: Python :: 3.10
Classifier: Programming Language :: Python :: 3.11
Classifier: Programming Language :: Python :: 3.12
Classifier: Topic :: Software Development :: Libraries :: Python Modules
Classifier: Typing :: Typed
Requires-Python: >=3.10
License-File: LICENCE
Requires-Dist: jinja2
Requires-Dist: pyyaml
Requires-Dist: types-pyyaml
Requires-Dist: lxml
Dynamic: license-file
